jupyter_client/__init__.py
jupyter_client/_version.py
jupyter_client/adapter.py
jupyter_client/channels.py
jupyter_client/channelsabc.py
jupyter_client/client.py
jupyter_client/clientabc.py
jupyter_client/connect.py
jupyter_client/consoleapp.py
jupyter_client/jsonutil.py
jupyter_client/kernelapp.py
jupyter_client/kernelspec.py
jupyter_client/kernelspecapp.py
jupyter_client/launcher.py
jupyter_client/localinterfaces.py
jupyter_client/manager.py
jupyter_client/managerabc.py
jupyter_client/multikernelmanager.py
jupyter_client/py.typed
jupyter_client/restarter.py
jupyter_client/runapp.py
jupyter_client/session.py
jupyter_client/threaded.py
jupyter_client/utils.py
jupyter_client/win_interrupt.py
jupyter_client/asynchronous/__init__.py
jupyter_client/asynchronous/client.py
jupyter_client/blocking/__init__.py
jupyter_client/blocking/client.py
jupyter_client/ioloop/__init__.py
jupyter_client/ioloop/manager.py
jupyter_client/ioloop/restarter.py
jupyter_client/provisioning/__init__.py
jupyter_client/provisioning/factory.py
jupyter_client/provisioning/local_provisioner.py
jupyter_client/provisioning/provisioner_base.py
jupyter_client/ssh/__init__.py
jupyter_client/ssh/forward.py
jupyter_client/ssh/tunnel.py
jupyter_client/tests/__init__.py
jupyter_client/tests/conftest.py
jupyter_client/tests/problemkernel.py
jupyter_client/tests/signalkernel.py
jupyter_client/tests/test_adapter.py
jupyter_client/tests/test_client.py
jupyter_client/tests/test_connect.py
jupyter_client/tests/test_jsonutil.py
jupyter_client/tests/test_kernelapp.py
jupyter_client/tests/test_kernelmanager.py
jupyter_client/tests/test_kernelspec.py
jupyter_client/tests/test_localinterfaces.py
jupyter_client/tests/test_manager.py
jupyter_client/tests/test_multikernelmanager.py
jupyter_client/tests/test_provisioning.py
jupyter_client/tests/test_public_api.py
jupyter_client/tests/test_restarter.py
jupyter_client/tests/test_session.py
jupyter_client/tests/test_ssh.py
jupyter_client/tests/utils.py
jupyter_client-7.4.0.dist-info/METADATA
jupyter_client-7.4.0.dist-info/WHEEL
jupyter_client-7.4.0.dist-info/entry_points.txt
jupyter_client-7.4.0.dist-info/licenses/COPYING.md
jupyter_client-7.4.0.dist-info/RECORD
