Metadata-Version: 2.1
Name: jupyter_client
Version: 7.4.0
Summary: Jupyter protocol implementation and client libraries
Project-URL: Homepage, https://jupyter.org
Author-email: Jupyter Development Team <jupyter@googlegroups.com>
License: # Licensing terms
License-File: COPYING.md
Keywords: Interactive,Interpreter,Shell,Web
Classifier: Framework :: Jupyter
Classifier: Intended Audience :: Developers
Classifier: Intended Audience :: Education
Classifier: Intended Audience :: Science/Research
Classifier: Intended Audience :: System Administrators
Classifier: License :: OSI Approved :: BSD License
Classifier: Operating System :: OS Independent
Classifier: Programming Language :: Python
Classifier: Programming Language :: Python :: 3
Classifier: Programming Language :: Python :: 3.7
Classifier: Programming Language :: Python :: 3.8
Classifier: Programming Language :: Python :: 3.9
Classifier: Programming Language :: Python :: 3.10
Requires-Python: >=3.7
Requires-Dist: entrypoints
Requires-Dist: jupyter-core>=4.9.2
Requires-Dist: nest-asyncio>=1.5.4
Requires-Dist: python-dateutil>=2.8.2
Requires-Dist: pyzmq>=23.0
Requires-Dist: tornado>=6.2
Requires-Dist: traitlets
Provides-Extra: doc
Requires-Dist: ipykernel; extra == 'doc'
Requires-Dist: myst-parser; extra == 'doc'
Requires-Dist: sphinx-rtd-theme; extra == 'doc'
Requires-Dist: sphinx>=1.3.6; extra == 'doc'
Requires-Dist: sphinxcontrib-github-alt; extra == 'doc'
Provides-Extra: test
Requires-Dist: codecov; extra == 'test'
Requires-Dist: coverage; extra == 'test'
Requires-Dist: ipykernel>=6.5; extra == 'test'
Requires-Dist: ipython; extra == 'test'
Requires-Dist: mypy; extra == 'test'
Requires-Dist: pre-commit; extra == 'test'
Requires-Dist: pytest; extra == 'test'
Requires-Dist: pytest-asyncio>=0.18; extra == 'test'
Requires-Dist: pytest-cov; extra == 'test'
Requires-Dist: pytest-timeout; extra == 'test'
